MANIFEST.in
README.md
pyproject.toml
setup.cfg
setup.py
Selenium4R/__init__.py
Selenium4R/webdriver.py
Selenium4R/webelement.py
Selenium4R.egg-info/PKG-INFO
Selenium4R.egg-info/SOURCES.txt
Selenium4R.egg-info/dependency_links.txt
Selenium4R.egg-info/requires.txt
Selenium4R.egg-info/top_level.txt
Selenium4R/common/JavaScriptLibrary.py
Selenium4R/common/__init__.py