Metadata-Version: 2.1
Name: Selenium4R
Version: 0.1.2
Summary: Selenium for Researcher
Home-page: https://github.com/ChangxingJiang/Selenium4R
Author: ChangXing
Author-email: 1278729001@qq.com
License: UNKNOWN
Keywords: selenium
Platform: UNKNOWN
Classifier: Development Status :: 3 - Alpha
Classifier: License :: OSI Approved :: MIT License
Classifier: Programming Language :: Python :: 3.8
Classifier: Programming Language :: Python
